langgraph_supervisor-0.0.28.dist-info/METADATA
langgraph_supervisor-0.0.28.dist-info/WHEEL
langgraph_supervisor-0.0.28.dist-info/entry_points.txt
langgraph_supervisor-0.0.28.dist-info/licenses/LICENSE
langgraph_supervisor/__init__.py
langgraph_supervisor/agent_name.py
langgraph_supervisor/handoff.py
langgraph_supervisor/py.typed
langgraph_supervisor/supervisor.py
langgraph_supervisor-0.0.28.dist-info/RECORD
